[
  {
    "question": "学校教育の目的や目標を達成するために、教育の内容を子供の心身の発達に応じ、授業時数との関連において＿＿＿に組織した学校の教育計画",
    "correct_answer": "総合的",
    "choices": [
      {
        "text": "総合的",
        "explanation": "教育内容を全体として体系的にまとめるという意味で正しい。"
      },
      {
        "text": "断片的",
        "explanation": "内容がバラバラになっており、教育計画として不適切。"
      },
      {
        "text": "無計画",
        "explanation": "教育計画という語に反し、計画性がないため明確に不正解。"
      },
      {
        "text": "即興的",
        "explanation": "その場しのぎの印象があり、計画的に教育を組織する意図に合わない。"
      },
      {
        "text": "部分的",
        "explanation": "全体を見据えず、一部だけを重視する意味になるため不適切。"
      },
      {
        "text": "限定的",
        "explanation": "限定された範囲にとどまり、教育の幅広さや全体性が失われるため不適切。"
      }
    ],
    "src_title": "次期学習指導要領等に向けたこれまでの審議のまとめ",
    "src_link": "courseofstudy2020-summary.md"
  },
  {
    "question": "「主体的・対話的で深い学び」の実現とは、人間の生涯にわたって続く「学び」という営みの本質を捉えながら、教員が教えることにしっかりと関わり、子供たちに求められる＿＿＿・能力を育むために必要な学びの在り方を絶え間なく考え、授業の工夫・改善を重ねていくことである。",
    "correct_answer": "資質",
    "choices": [
      {
        "text": "資質",
        "explanation": "子供たちに備わるべき素養や性質を指し、文脈上正しい。"
      },
      {
        "text": "知識",
        "explanation": "学習内容として重要だが、文脈では能力と対になる語は資質。"
      },
      {
        "text": "人格",
        "explanation": "人間性を表現する語だが、学びの実現に直接結びつかない。"
      },
      {
        "text": "態度",
        "explanation": "学びに必要な姿勢ともいえるが、能力と対になる語ではない。"
      },
      {
        "text": "技術",
        "explanation": "能力の一面を指すが、資質の方が文脈に適切。"
      },
      {
        "text": "経験",
        "explanation": "学びの結果増えていくものだが、能力の対比語にはならない。"
      }
    ],
    "src_title": "次期学習指導要領等に向けたこれまでの審議のまとめ",
    "src_link": "courseofstudy2020-summary.md"
  },
  {
    "question": "生徒指導とは、一人一人の児童生徒の人格を尊重し、個性の伸長を図りながら、＿＿＿や行動力を高めることを目指して行われる教育活動のことである。",
    "correct_answer": "社会的資質",
    "choices": [
      {
        "text": "社会的資質",
        "explanation": "原文通りであり、生徒指導が目指す力として正しい。"
      },
      {
        "text": "運動能力",
        "explanation": "生徒指導の文脈では主目的でなく、文意から外れている。"
      },
      {
        "text": "学習成果",
        "explanation": "学力や学習の成果は別分野で、生徒指導の目的とは異なる。"
      },
      {
        "text": "芸術的感性",
        "explanation": "芸術分野に限定されており、社会性を高める意味から外れている。"
      },
      {
        "text": "趣味嗜好",
        "explanation": "個人の嗜好に関する語であり、教育活動の目標とはならない。"
      },
      {
        "text": "情報処理能力",
        "explanation": "特定のスキルであり、原文の「社会的資質」とは趣旨が異なる。"
      }
    ],
    "src_title": "次期学習指導要領等に向けたこれまでの審議のまとめ",
    "src_link": "courseofstudy2020-summary.md"
  },
  {
    "question": "新たな価値とは、グローバルな規模でのイノベーションのような大規模なものに限られるものではなく、地域課題や身近な生活上の課題を自分なりに解決し、自他の人生や生活を＿＿＿ものとしていくという様々な工夫なども含むものである",
    "correct_answer": "豊かな",
    "choices": [
      {
        "text": "豊かな",
        "explanation": "人生や生活をより良いものにすることという文脈に適しているため正解。"
      },
      {
        "text": "厳しい",
        "explanation": "困難な状況を強調する語であり、価値創造の意味と合致しないため不正解。"
      },
      {
        "text": "単調な",
        "explanation": "変化や工夫がない様子を示す語で、価値創造を阻むため不正解。"
      },
      {
        "text": "限定的な",
        "explanation": "幅や多様性を制限する語で、多様な価値を含む趣旨に反するため不正解。"
      },
      {
        "text": "消極的な",
        "explanation": "前向きな取り組みとは逆の意味を含み、文脈に合わないため不正解。"
      },
      {
        "text": "消えやすい",
        "explanation": "価値が持続しない印象を与え、価値創造の趣旨に反するため不正解。"
      }
    ],
    "src_title": "次期学習指導要領等に向けたこれまでの審議のまとめ",
    "src_link": "courseofstudy2020-summary.md"
  },
  {
    "question": "生きる力とは、国際化や情報化の進展など、変化が激しい時代にあって、いかに社会が変化しようと必要な能力、知・徳・体のバランスの取れた＿＿＿である",
    "correct_answer": "力",
    "choices": [
      {
        "text": "力",
        "explanation": "知・徳・体のバランスの取れた“力”が本来の語句であり、文章の意味に合う。"
      },
      {
        "text": "知識",
        "explanation": "“知”に偏った表現であり、「知・徳・体のバランス」という文脈に合わない。"
      },
      {
        "text": "態度",
        "explanation": "“徳”や“体”を十分に含まず、バランスの取れた力全体を表せない。"
      },
      {
        "text": "方法",
        "explanation": "能力や資質を表す“力”の代わりにはならず、意味がずれる。"
      },
      {
        "text": "技能",
        "explanation": "主に“体”や一部の“知”に関わるが、“徳”を含まず、全体的なバランスを表現できない。"
      },
      {
        "text": "動機",
        "explanation": "意欲や内発的な要因を示すが、知・徳・体の総合的な力には該当しない。"
      }
    ],
    "src_title": "これまで提言された様々な資質・能力について（イメージ案）",
    "src_link": "https://www.mext.go.jp/b_menu/shingi/chousa/shotou/095/shiryo/__icsFiles/afieldfile/2012/12/18/1329013_02.pdf"
  },
  {
    "question": "「インクルーシブ教育システムとは、人間の多様性の尊重等を強化し、障害者が精神的及び身体的な能力等を可能な最大限度まで発達させ、自由な社会に効果的に参加することを可能とするとの目的の下、障害のある者と障害のない者が共に＿＿＿仕組みである」",
    "correct_answer": "学ぶ",
    "choices": [
      {
        "text": "学ぶ",
        "explanation": "インクルーシブ教育は共に教育を受けることが目的であり、文脈上正しい表現。"
      },
      {
        "text": "遊ぶ",
        "explanation": "インクルーシブな関わりを示すが、教育システムの主眼は『学ぶ』ことなので不適切。"
      },
      {
        "text": "働く",
        "explanation": "仕事の場面を示唆し、教育の文脈に合っていない。"
      },
      {
        "text": "住む",
        "explanation": "生活空間を共にするという意味だが、教育システムの主旨とは異なる。"
      },
      {
        "text": "競争する",
        "explanation": "協働や共生の文脈ではなく、対立を想起させるため不適切。"
      },
      {
        "text": "支配する",
        "explanation": "上下関係や強制を感じさせ、平等や共生を目的とするインクルーシブ教育には相応しくない。"
      }
    ],
    "src_title": "次期学習指導要領等に向けたこれまでの審議のまとめ",
    "src_link": "courseofstudy2020-summary.md"
  },
  {
    "question": "キャリア教育とは、一人一人の社会的・職業的自立に向け、必要な基盤となる能力や態度を育てることを通じて、＿＿＿を促す教育のことである",
    "correct_answer": "キャリア発達",
    "choices": [
      {
        "text": "キャリア発達",
        "explanation": "キャリア教育の目的そのものであり、本文の文脈に完全に合致する。"
      },
      {
        "text": "学力向上",
        "explanation": "教育の一般的な目標だが、キャリア教育の直接的な目的とは異なるため不正解。"
      },
      {
        "text": "進学率向上",
        "explanation": "進学とキャリア発達は別概念で、キャリア教育の趣旨とは異なる。"
      },
      {
        "text": "社会福祉",
        "explanation": "社会全体の福祉向上も重要だが、キャリア教育の定義とは直接関係しない。"
      },
      {
        "text": "専門知識習得",
        "explanation": "知識の習得も一部ではあるが、キャリア教育の主目的は“発達”であり不十分。"
      },
      {
        "text": "人格形成",
        "explanation": "人格の発達も重要だが、キャリア教育では“キャリア発達”が主となるため不正解。"
      }
    ],
    "src_title": "次期学習指導要領等に向けたこれまでの審議のまとめ",
    "src_link": "courseofstudy2020-summary.md"
  },
  {
    "question": "「単元とは、各教科等において、一定の目標や主題を中心として組織された学習内容の＿＿＿なひとまとまりのことである」",
    "correct_answer": "有機的",
    "choices": [
      {
        "text": "有機的",
        "explanation": "全体が意味ある関係で結びついて構成されていることを表し、定義として正しい。"
      },
      {
        "text": "機械的",
        "explanation": "自動的・無機質に組織するという意味で、文意と合わず不適切。"
      },
      {
        "text": "形式的",
        "explanation": "形だけ・表面的にまとまっていることを表し、内容の関連性が薄くなるため不正解。"
      },
      {
        "text": "部分的",
        "explanation": "全体ではなく一部だけを言う語であり、「ひとまとまり」の意味に合わない。"
      },
      {
        "text": "偶発的",
        "explanation": "偶然的にまとまる意であり、計画的な組織性を重視する定義に反する。"
      },
      {
        "text": "断片的",
        "explanation": "バラバラでつながりがない様子を表し、「ひとまとまり」という説明と矛盾する。"
      }
    ],
    "src_title": "次期学習指導要領等に向けたこれまでの審議のまとめ",
    "src_link": "courseofstudy2020-summary.md"
  },
  {
    "question": "「＿＿＿」とは、自分が意図する一連の活動を実現するために、どのような動きの組合せが必要であり、一つ一つの動きに対応した記号を、どのように組み合わせたらいいのか、記号の組合せをどのように改善していけば、より意図した活動に近づくのか、といったことを論理的に考えていく力のことである。",
    "correct_answer": "プログラミング的思考",
    "choices": [
      {
        "text": "プログラミング的思考",
        "explanation": "本文で定義されている中心的な語句であり、正しい。"
      },
      {
        "text": "計算力",
        "explanation": "計算に関する能力であり、記号の論理的組合せや思考力とは異なるため不正解。"
      },
      {
        "text": "読解力",
        "explanation": "文章の理解力を指し、論理的な記号の組合せや活動の設計には直接関係しない。"
      },
      {
        "text": "創造力",
        "explanation": "新しいものを生み出す力だが、論理的な組合せや計画性という点でやや趣旨が異なる。"
      },
      {
        "text": "観察力",
        "explanation": "物事をよく観る力であり、論理的な組合せや手順の設計とは直接結びつかない。"
      },
      {
        "text": "暗記力",
        "explanation": "知識を覚える力だが、組合せや論理的思考には直結しない。"
      }
    ],
    "src_title": "次期学習指導要領等に向けたこれまでの審議のまとめ",
    "src_link": "courseofstudy2020-summary.md"
  },
  {
    "question": "進路指導とは、生徒の個人資料、進路情報、啓発的経験及び相談を通じて、生徒が自ら、将来の進路を選択・計画し、就職又は進学をして、更にその後の生活によりよく適応し、能力を＿＿＿するように、教員が組織的・継続的に指導・援助する過程であり、どのような人間になり、どう生きていくことが望ましいのかといった長期的展望に立った人間形成を目指す教育活動である",
    "correct_answer": "伸長",
    "choices": [
      {
        "text": "伸長",
        "explanation": "「能力をさらに高める・発展させる」という意味で、文脈上正しい。"
      },
      {
        "text": "制限",
        "explanation": "「制限する」は能力を狭めることを意味し、文脈に合わず不正解。"
      },
      {
        "text": "減少",
        "explanation": "「能力を減らす」という意味になり、教育的意義と反対で不正解。"
      },
      {
        "text": "固定",
        "explanation": "「変化や発展がない」という意味になり、伸ばすべき能力にそぐわない。"
      },
      {
        "text": "停滞",
        "explanation": "進歩しない・先に進まないという意味で、教育の目的と逆の意味。"
      },
      {
        "text": "縮小",
        "explanation": "能力を小さくすることを意味し、文脈上不適切。"
      }
    ],
    "src_title": "次期学習指導要領等に向けたこれまでの審議のまとめ",
    "src_link": "courseofstudy2020-summary.md"
  },
  {
    "question": "「パスポートとは、公文書である＿＿＿という本来の意味を超えて、学びの履歴を積み重ねていくことにより、過去の履歴を振り返ったり、将来の学びの予定を考え積み重ねたりしていくことを支援する仕組みを指すものである」",
    "correct_answer": "旅券",
    "choices": [
      {
        "text": "旅券",
        "explanation": "パスポートの本来の意味であり、文脈に最も合致している。"
      },
      {
        "text": "証明書",
        "explanation": "身分証明書の一種ではあるが、パスポートの正式な呼称ではないため不正解。"
      },
      {
        "text": "通帳",
        "explanation": "銀行口座に関する書類であり、パスポートの説明とは全く異なる。"
      },
      {
        "text": "手帳",
        "explanation": "パスポートの形状には似ているが、用途や意味が異なるので不適切。"
      },
      {
        "text": "認定書",
        "explanation": "何かを認める書類だが、旅券（パスポート）の意味を表すものではない。"
      },
      {
        "text": "証拠書類",
        "explanation": "証拠を示す文書だが、パスポート（旅券）の具体的な意味や本来の呼称ではない。"
      }
    ],
    "src_title": "次期学習指導要領等に向けたこれまでの審議のまとめ",
    "src_link": "courseofstudy2020-summary.md"
  },
  {
    "question": "資質・能力の三つの柱とは、1. 「知識及び技能」の習得、2. 「思考力，判断力，表現力等」の育成、3. 「学びに向かう力，人間性等」の＿＿＿である。",
    "correct_answer": "涵養",
    "choices": [
      {
        "text": "涵養",
        "explanation": "『養い育てること』という意味で、三つの柱の説明文として正しい。"
      },
      {
        "text": "抑制",
        "explanation": "『抑え止めること』という意味で、育成や発展と逆の内容になり不適切。"
      },
      {
        "text": "固定",
        "explanation": "『変わらずに一定の状態にすること』であり、能力を育て伸ばす文脈に合わない。"
      },
      {
        "text": "制御",
        "explanation": "『コントロールする』の意味であり、人格や学ぶ力を育成する趣旨に沿わない。"
      },
      {
        "text": "削減",
        "explanation": "『減らす』という意味のため、能力を高める目的には不適切。"
      },
      {
        "text": "放棄",
        "explanation": "『やめてしまうこと』であり、人間性や学ぶ力を育てる文脈に正反対な語句。"
      }
    ],
    "src_title": "小学校学習指導要領（平成29年告示）解説 総則編 第３章 教育課程の編成及び実施",
    "src_link": "https://www.mext.go.jp/content/20230308-mxt_kyoiku02-100002607_001.pdf"
  },
  {
    "question": "教科等横断的な視点で育成を目指す資質・能力とは、1. 学習の基盤となる資質・能力 2. ＿＿＿な諸課題に対応して求められる資質・能力 3. などである",
    "correct_answer": "現代的",
    "choices": [
      {
        "text": "現代的",
        "explanation": "現代社会が直面する課題に対応するという文脈に合っており正しい。"
      },
      {
        "text": "古典的",
        "explanation": "文脈上、過去の課題を指す語であり、現代の課題と合致しない。"
      },
      {
        "text": "専門的",
        "explanation": "専門分野に特化した課題を指し、広い範囲の現代的課題を網羅できないため不適切。"
      },
      {
        "text": "個人的",
        "explanation": "個人レベルの課題を指しており、社会全体の現代的な諸課題と趣旨が異なる。"
      },
      {
        "text": "伝統的",
        "explanation": "伝統に根付いた過去の課題であり、現代の課題とは異なる。"
      },
      {
        "text": "限定的",
        "explanation": "範囲が限定されていることを示し、現代社会が抱える幅広い課題の意味と異なる。"
      }
    ],
    "src_title": "小学校学習指導要領（平成29年告示）解説 総則編 第３章 教育課程の編成及び実施",
    "src_link": "https://www.mext.go.jp/content/20230308-mxt_kyoiku02-100002607_001.pdf"
  },
  {
    "question": "学習の基盤となる資質・能力とは、1. 言語能力 2. 情報活用能力 3. ＿＿＿ 4. などである",
    "correct_answer": "問題発見・解決能力",
    "choices": [
      {
        "text": "問題発見・解決能力",
        "explanation": "学習の過程で重要な力であり、文章からも明示されているため正解。"
      },
      {
        "text": "計算能力",
        "explanation": "数学的分野の力であるが、学習全般の基盤には必ずしも当てはまらないため不正解。"
      },
      {
        "text": "運動能力",
        "explanation": "身体活動に関連する力であり、文章の文脈とは異なるため不正解。"
      },
      {
        "text": "協調性",
        "explanation": "集団生活で必要だが、文章中の「学習の基盤となる資質・能力」には挙げられていない。"
      },
      {
        "text": "創造力",
        "explanation": "重要な能力ではあるが、文章中で明示されたものではないため不正解。"
      },
      {
        "text": "記憶力",
        "explanation": "学習に必要だが、文章内の他の能力とは直接一致しないため不正解。"
      }
    ],
    "src_title": "小学校学習指導要領（平成29年告示）解説 総則編 第３章 教育課程の編成及び実施",
    "src_link": "https://www.mext.go.jp/content/20230308-mxt_kyoiku02-100002607_001.pdf"
  },
  {
    "question": "「＿＿＿とは、世の中の様々な事象を情報とその結び付きとして捉え、情報及び情報技術を適切かつ効果的に活用して、問題を発見・解決したり自分の考えを形成したりしていくために必要な資質・能力である」",
    "correct_answer": "情報活用能力",
    "choices": [
      {
        "text": "情報活用能力",
        "explanation": "文章の定義にあたるものであり、正しい。"
      },
      {
        "text": "学力",
        "explanation": "学力は広い概念であり、具体的な定義に一致しないため不正解。"
      },
      {
        "text": "情報リテラシー",
        "explanation": "似た意味を持つが、文章が定義している語句とは異なるため不正解。"
      },
      {
        "text": "ITスキル",
        "explanation": "IT技術のみを指し、文章の幅広い資質・能力の意味に合わない。"
      },
      {
        "text": "問題解決能力",
        "explanation": "一部の内容に該当するが、全体の定義に一致しない。"
      },
      {
        "text": "コミュニケーション能力",
        "explanation": "文章で述べられる要素の一部だが、主要な定義と異なるため不適切。"
      }
    ],
    "src_title": "小学校学習指導要領（平成29年告示）解説 総則編 第３章 教育課程の編成及び実施",
    "src_link": "https://www.mext.go.jp/content/20230308-mxt_kyoiku02-100002607_001.pdf"
  },
  {
    "question": "情報モラルとは、情報社会で適正な活動を行うための基になる＿＿＿と態度である",
    "correct_answer": "考え方",
    "choices": [
      {
        "text": "考え方",
        "explanation": "情報モラルの根本を成すものであり、正しい。"
      },
      {
        "text": "知識",
        "explanation": "知識も重要だが、モラルの根本は考え方であるため不正解。"
      },
      {
        "text": "意見",
        "explanation": "個人の意見ではなく、普遍的な考え方が求められるため不正解。"
      },
      {
        "text": "能力",
        "explanation": "能力は実践に関するものであり、モラルの基ではない。"
      },
      {
        "text": "規則",
        "explanation": "規則は外部から与えられるものであり、モラルの内面性とは異なる。"
      },
      {
        "text": "技術",
        "explanation": "技術は知識や能力と関連するが、情報モラルの根幹ではないため不正解。"
      }
    ],
    "src_title": "小学校学習指導要領（平成29年告示）解説 総則編 第３章 教育課程の編成及び実施",
    "src_link": "https://www.mext.go.jp/content/20230308-mxt_kyoiku02-100002607_001.pdf"
  },
  {
    "question": "カリキュラム・マネジメントとは、児童や学校，地域の実態を適切に把握し，教育の目的や目標の実現に必要な教育の内容等を教科等横断的な視点で＿＿＿に組み立てていくこと，教育課程の実施状況を評価してその改善を図っていくこと，教育課程の実施に必要な人的又は物的な体制を確保するとともにその改善を図っていくことなどを通して，教育課程に基づき組織的かつ計画的に各学校の教育活動の質の向上を図っていくことである",
    "correct_answer": "横断的",
    "choices": [
      {
        "text": "横断的",
        "explanation": "複数の教科や内容領域をまたいで全体的に組み立てるという意味で正しい。"
      },
      {
        "text": "単独的",
        "explanation": "一つの教科や内容のみを対象にする語であり、文脈に合わない。"
      },
      {
        "text": "偶発的",
        "explanation": "偶然に起こるという意味で、計画的に組み立てるという趣旨に反する。"
      },
      {
        "text": "断片的",
        "explanation": "内容がバラバラで統一がないことを指し、教育課程の趣旨に合わない。"
      },
      {
        "text": "部分的",
        "explanation": "全体の一部のみを扱う語であり、横断的な視点の反対。"
      },
      {
        "text": "限定的",
        "explanation": "範囲が狭いという意味で、多様な教科等を組み立てる趣旨に反する。"
      }
    ],
    "src_title": "小学校学習指導要領（平成29年告示）解説 総則編 第３章 教育課程の編成及び実施",
    "src_link": "https://www.mext.go.jp/content/20230308-mxt_kyoiku02-100002607_001.pdf"
  },
  {
    "question": "「＿＿＿とは、言葉は、児童の学習活動を支える重要な役割を果たすものであり，全ての教科等における資質・能力の育成や学習の基盤となるものである」",
    "correct_answer": "言語能力",
    "choices": [
      {
        "text": "言語能力",
        "explanation": "文章の冒頭で説明の対象となっており、文意に最も合致する。"
      },
      {
        "text": "運動能力",
        "explanation": "身体的な力であり、言葉や学習活動の支えとしては不適切。"
      },
      {
        "text": "創造力",
        "explanation": "新しいものを生み出す力であり、言葉や学習活動の基盤という文脈とはずれる。"
      },
      {
        "text": "計算能力",
        "explanation": "数学的な能力であって、全ての教科や学習の基盤として一般的ではない。"
      },
      {
        "text": "読解力",
        "explanation": "文章を読む力であり、言語能力の一部ではあるが、全体の基盤という説明とは合致しない。"
      },
      {
        "text": "社会性",
        "explanation": "他者と関わる力であり、言葉や学習の直接的な基盤とは言えない。"
      }
    ],
    "src_title": "小学校学習指導要領（平成29年告示）解説 総則編 第３章 教育課程の編成及び実施",
    "src_link": "https://www.mext.go.jp/content/20230308-mxt_kyoiku02-100002607_001.pdf"
  },
  {
    "question": "「探究的な学習とは、問題解決的な活動（課題の設定、情報の収集、整理・分析、まとめ・表現）が＿＿＿に繰り返されていくことである」",
    "correct_answer": "発展的",
    "choices": [
      {
        "text": "発展的",
        "explanation": "学習活動が発展し続けながら繰り返されることを表し、文脈に合致している。"
      },
      {
        "text": "形式的",
        "explanation": "ただ形だけの繰り返しとなり、学習の深まりを意味しないため不正解。"
      },
      {
        "text": "単純的",
        "explanation": "活動が単純に繰り返されるという意味で、探究的な学習の趣旨に合わない。"
      },
      {
        "text": "一時的",
        "explanation": "短期間で一度きりの活動のような印象となり、継続的な学習を示さない。"
      },
      {
        "text": "消極的",
        "explanation": "積極的に取り組む学習活動と対立する言葉なので不適切。"
      },
      {
        "text": "偶発的",
        "explanation": "偶然発生する活動という意味になり、計画的に繰り返される学習の文脈に合わない。"
      }
    ],
    "src_title": "小学校学習指導要領（平成 29 年告示）解説 総合的な学習の時間編",
    "src_link": "https://www.mext.go.jp/component/a_menu/education/micro_detail/__icsFiles/afieldfile/2019/03/18/1387017_013_1.pdf"
  }
]